argos/__init__.py
argos/__main__.py
argos/application.py
argos/argos_make_wrappers.py
argos/info.py
argos/main.py
argos/mytest.py
argos/collect/__init__.py
argos/collect/collector.py
argos/collect/collectortree.py
argos/config/__init__.py
argos/config/abstractcti.py
argos/config/boolcti.py
argos/config/choicecti.py
argos/config/configitemdelegate.py
argos/config/configtreemodel.py
argos/config/configtreeview.py
argos/config/floatcti.py
argos/config/groupcti.py
argos/config/intcti.py
argos/config/qtctis.py
argos/config/stringcti.py
argos/config/untypedcti.py
argos/external/__init__.py
argos/external/json_with_comments.py
argos/external/six.py
argos/img/argos.css
argos/img/snipicons/README.txt
argos/img/snipicons/align-left.svg
argos/img/snipicons/arrow-down-l.svg
argos/img/snipicons/arrow-left-l.svg
argos/img/snipicons/arrow-right-l.svg
argos/img/snipicons/arrow-up-l.svg
argos/img/snipicons/asterisk.svg
argos/img/snipicons/circle-arrow-down-l.svg
argos/img/snipicons/circle-arrow-left-l.svg
argos/img/snipicons/circle-arrow-right-l.svg
argos/img/snipicons/circle-arrow-up-l.svg
argos/img/snipicons/exclamation-sign.svg
argos/img/snipicons/file-inverse.svg
argos/img/snipicons/file.svg
argos/img/snipicons/folder-close.svg
argos/img/snipicons/folder-open.svg
argos/img/snipicons/leaf.svg
argos/img/snipicons/list.svg
argos/img/snipicons/minus-l.svg
argos/img/snipicons/minus-sign-l.svg
argos/img/snipicons/move.svg
argos/img/snipicons/plus-sign-l.svg
argos/img/snipicons/remove-circle-l.svg
argos/img/snipicons/remove-sign-l.svg
argos/img/snipicons/reset-l.svg
argos/img/snipicons/th-large.svg
argos/img/snipicons/th-list.svg
argos/img/snipicons/transparent_1x1.svg
argos/img/snipicons/warning-sign.svg
argos/inspector/__init__.py
argos/inspector/abstract.py
argos/inspector/debug.py
argos/inspector/dialog.py
argos/inspector/errormsg.py
argos/inspector/registry.py
argos/inspector/selectionpane.py
argos/inspector/pgplugins/__init__.py
argos/inspector/pgplugins/colorbar.py
argos-0.4.5.dist-info/licenses/LICENSE
argos-0.4.5.dist-info/METADATA
argos-0.4.5.dist-info/WHEEL
argos-0.4.5.dist-info/entry_points.txt
argos-0.4.5.dist-info/top_level.txt
argos-0.4.5.dist-info/RECORD
